{
  "main": {
    "id": "31aa5d39d6194a77",
    "type": "split",
    "children": [
      {
        "id": "f1f6f93c625d8c53",
        "type": "tabs",
        "children": [
          {
            "id": "79c7c8e72b4e192a",
            "type": "leaf",
            "state": {
              "type": "markdown",
              "state": {
                "file": "People/Qi Haixia.md",
                "mode": "source",
                "source": false
              },
              "icon": "lucide-file",
              "title": "Qi Haixia"
            }
          },
          {
            "id": "b2b5eb03f9ffe3e0",
            "type": "leaf",
            "state": {
              "type": "markdown",
              "state": {
                "file": "Moral Realism.md",
                "mode": "source",
                "source": false
              },
              "icon": "lucide-file",
              "title": "Moral Realism"
            }
          },
          {
            "id": "5cb312f4a4cffe09",
            "type": "leaf",
            "state": {
              "type": "markdown",
              "state": {
                "file": "Structural Realism.md",
                "mode": "source",
                "source": false
              },
              "icon": "lucide-file",
              "title": "Structural Realism"
            }
          },
          {
            "id": "2fddd19798a63b58",
            "type": "leaf",
            "state": {
              "type": "graph",
              "state": {},
              "icon": "lucide-git-fork",
              "title": "Podgląd grafu"
            }
          },
          {
            "id": "8c9f1ced8cb9b3ed",
            "type": "leaf",
            "state": {
              "type": "graph",
              "state": {},
              "icon": "lucide-git-fork",
              "title": "Podgląd grafu"
            }
          },
          {
            "id": "7a49b17675ce78d2",
            "type": "leaf",
            "state": {
              "type": "markdown",
              "state": {
                "file": "Intermediate Variable.md",
                "mode": "source",
                "source": false
              },
              "icon": "lucide-file",
              "title": "Intermediate Variable"
            }
          },
          {
            "id": "873a144bd854dab2",
            "type": "leaf",
            "state": {
              "type": "graph",
              "state": {},
              "icon": "lucide-git-fork",
              "title": "Podgląd grafu"
            }
          },
          {
            "id": "c9779e0c5864dc9a",
            "type": "leaf",
            "state": {
              "type": "graph",
              "state": {},
              "icon": "lucide-git-fork",
              "title": "Podgląd grafu"
            }
          },
          {
            "id": "61610a34c2dbb891",
            "type": "leaf",
            "state": {
              "type": "graph",
              "state": {},
              "icon": "lucide-git-fork",
              "title": "Podgląd grafu"
            }
          },
          {
            "id": "4d275a32ce54c756",
            "type": "leaf",
            "state": {
              "type": "markdown",
              "state": {
                "file": "Neo-colonial.md",
                "mode": "source",
                "source": false
              },
              "icon": "lucide-file",
              "title": "Neo-colonial"
            }
          },
          {
            "id": "c8ba4a4eb15b8cc0",
            "type": "leaf",
            "state": {
              "type": "markdown",
              "state": {
                "file": "Prestige.md",
                "mode": "source",
                "source": false
              },
              "icon": "lucide-file",
              "title": "Prestige"
            }
          },
          {
            "id": "63a17bef157b720f",
            "type": "leaf",
            "state": {
              "type": "graph",
              "state": {},
              "icon": "lucide-git-fork",
              "title": "Podgląd grafu"
            }
          },
          {
            "id": "f0ce2b2a3ed1d861",
            "type": "leaf",
            "state": {
              "type": "markdown",
              "state": {
                "file": "Anarchical World System.md",
                "mode": "source",
                "source": false
              },
              "icon": "lucide-file",
              "title": "Anarchical World System"
            }
          },
          {
            "id": "9384ebebf995b8d4",
            "type": "leaf",
            "state": {
              "type": "markdown",
              "state": {
                "file": "Overwelming alliance.md",
                "mode": "source",
                "source": false
              },
              "icon": "lucide-file",
              "title": "Overwelming alliance"
            }
          },
          {
            "id": "85e7d632bd4d3a09",
            "type": "leaf",
            "state": {
              "type": "markdown",
              "state": {
                "file": "Ken Booth.md",
                "mode": "source",
                "source": false
              },
              "icon": "lucide-file",
              "title": "Ken Booth"
            }
          },
          {
            "id": "a6282624b5011cea",
            "type": "leaf",
            "state": {
              "type": "markdown",
              "state": {
                "file": "Relational Theory.md",
                "mode": "source",
                "source": false
              },
              "icon": "lucide-file",
              "title": "Relational Theory"
            }
          }
        ],
        "currentTab": 11
      }
    ],
    "direction": "vertical"
  },
  "left": {
    "id": "1e49b0d7c26da197",
    "type": "split",
    "children": [
      {
        "id": "6693b5c53f5db0e0",
        "type": "tabs",
        "children": [
          {
            "id": "433efd3e5b23a8b9",
            "type": "leaf",
            "state": {
              "type": "file-explorer",
              "state": {
                "sortOrder": "alphabetical",
                "autoReveal": true
              },
              "icon": "lucide-folder-closed",
              "title": "Przeglądarka plików"
            }
          },
          {
            "id": "9e955c150d5a88cb",
            "type": "leaf",
            "state": {
              "type": "search",
              "state": {
                "query": "tag:#Main_Authors",
                "matchingCase": false,
                "explainSearch": false,
                "collapseAll": false,
                "extraContext": false,
                "sortOrder": "alphabetical"
              },
              "icon": "lucide-search",
              "title": "Wyszukiwarka"
            }
          },
          {
            "id": "98f1218a592c770f",
            "type": "leaf",
            "state": {
              "type": "bookmarks",
              "state": {},
              "icon": "lucide-bookmark",
              "title": "Ulubione"
            }
          }
        ]
      }
    ],
    "direction": "horizontal",
    "width": 300
  },
  "right": {
    "id": "45eda85b3bb214a4",
    "type": "split",
    "children": [
      {
        "id": "3103a547648c75c9",
        "type": "tabs",
        "children": [
          {
            "id": "4debeb9d3f77a2fe",
            "type": "leaf",
            "state": {
              "type": "backlink",
              "state": {
                "collapseAll": false,
                "extraContext": false,
                "sortOrder": "alphabetical",
                "showSearch": false,
                "searchQuery": "",
                "backlinkCollapsed": false,
                "unlinkedCollapsed": true
              },
              "icon": "links-coming-in",
              "title": "Linki zwrotne"
            }
          },
          {
            "id": "1c39a32eba073f93",
            "type": "leaf",
            "state": {
              "type": "outgoing-link",
              "state": {
                "file": "Imperialism as a special stage of capitalism.md",
                "linksCollapsed": false,
                "unlinkedCollapsed": true
              },
              "icon": "links-going-out",
              "title": "Łącza wychodzące od Imperialism as a special stage of capitalism"
            }
          },
          {
            "id": "fe33b61344182f15",
            "type": "leaf",
            "state": {
              "type": "tag",
              "state": {
                "sortOrder": "frequency",
                "useHierarchy": true,
                "showSearch": false,
                "searchQuery": ""
              },
              "icon": "lucide-tags",
              "title": "Tagi"
            }
          },
          {
            "id": "0fc8e0405a6ba0e7",
            "type": "leaf",
            "state": {
              "type": "all-properties",
              "state": {
                "sortOrder": "frequency",
                "showSearch": false,
                "searchQuery": ""
              },
              "icon": "lucide-archive",
              "title": "Wszystkie atrybuty"
            }
          },
          {
            "id": "b43fe02abed8affc",
            "type": "leaf",
            "state": {
              "type": "outline",
              "state": {
                "file": "Imperialism as a special stage of capitalism.md",
                "followCursor": false,
                "showSearch": false,
                "searchQuery": ""
              },
              "icon": "lucide-list",
              "title": "Konspekt Imperialism as a special stage of capitalism"
            }
          }
        ]
      }
    ],
    "direction": "horizontal",
    "width": 300
  },
  "left-ribbon": {
    "hiddenItems": {
      "graph:Otwórz podgląd grafu": false,
      "switcher:Otwórz okno szybkiego wyboru": false,
      "canvas:Stwórz nową tablicę": false,
      "daily-notes:Otwórz dzisiejszy dziennik": false,
      "templates:Wstaw szablon": false,
      "command-palette:Otwórz listę poleceń": false,
      "bases:Stwórz nową bazę danych": false
    }
  },
  "active": "63a17bef157b720f",
  "lastOpenFiles": [
    "Prestige.md",
    "The Struggle for Power.md",
    "Power.md",
    "załączniki/The Struggle for Power - Policy of Prestiege.docx",
    "załączniki/~$e Struggle for Power - Policy of Prestiege 1.docx",
    "załączniki/The Struggle for Power - Policy of Prestiege 2.docx",
    "załączniki/The Struggle for Power - Policy of Prestiege 1.docx",
    "Doctrines.md",
    "Three Warfares.md",
    "Grand Strategy.md",
    "Chinese debt trap diplomacy in Africa the experience of Ghana.md",
    "załączniki/~WRL1959.tmp",
    "załączniki/~WRD1943.tmp",
    "załączniki/~$inese debt trap diplomacy in Africa the experience of Ghana - Kwame Asah Asante 1.docx",
    "załączniki/Chinese debt trap diplomacy in Africa the experience of Ghana - Kwame Asah Asante 1.docx",
    "Neo-colonial.md",
    "załączniki/~$inese debt trap diplomacy in Africa the experience of Ghana - Kwame Asah Asante.docx",
    "załączniki/Chinese debt trap diplomacy in Africa the experience of Ghana - Kwame Asah Asante.docx",
    "Tianxia and Its Decolonial Counterparts.md",
    "Lawfare.md",
    "China.md",
    "Tools.md",
    "Off-shore balancing.md",
    "Selective contestation.md",
    "Xunzi.md",
    "Kautilya.md",
    "Anarchical World System.md",
    "Yaqing Qin.md",
    "Ministers.md",
    "Intermediate Variable.md",
    "People/Yan Xuetong.md",
    "How Do Xunzi and Kautilya Ponder Interstate Politics.md",
    "Master Variable.md",
    "Glory.md",
    "Power Transition Theory.md",
    "Structural Realism.md"
  ]
}